negara_007info/__init__.py
negara_007info/country_007info.py
negara_info/__init__.py
negara_info/country_info.py
country_007info-0.0.2.dist-info/LICENSE
country_007info-0.0.2.dist-info/METADATA
country_007info-0.0.2.dist-info/WHEEL
country_007info-0.0.2.dist-info/top_level.txt
country_007info-0.0.2.dist-info/RECORD
