Metadata-Version: 2.1
Name: country-007info
Version: 0.0.2
Summary: Inform Country
Home-page: https://github.com/syahrulcaem/Informasi_negara
Author: scaem007
Author-email: <syahrulromadhonmuhamamd@gmail.com>
License: MIT
Keywords: country
Classifier: Development Status :: 1 - Planning
License-File: LICENSE
